<?xml version="1.0"?>

<PropertyList>

  <submodel> 
    <name>parachutist</name>
    <model>Models/Geometry/parachuter.xml</model>
    <trigger>controls/jump-signal</trigger>
    <speed>0</speed>
    <repeat>true</repeat>
    <delay>2</delay>
    <count>10</count>
    <x-offset>-65</x-offset>
    <y-offset>-8</y-offset>
    <z-offset>-11</z-offset>
    <yaw-offset>0.0</yaw-offset>
    <pitch-offset>0.0</pitch-offset>
    <cd>1.2</cd>
    <eda>100</eda>
    <weight>200</weight>
    <wind>true</wind>
    <buoyancy>20</buoyancy>
    <life>600</life>
  </submodel>

</PropertyList>
